{
  "yama/datunshan-2025/KCS01391.jpg": [
    {
      "name": "大屯山南峰",
      "x": 45.99,
      "y": 68.09
    }
  ],
  "yama/datunshan-2025/KCS01401.jpg": [
    {
      "name": "大屯山南峰",
      "x": 75.64,
      "y": 68.11
    }
  ],
  "yama/datunshan-2025/KCS01410.jpg": [
    {
      "name": "七星山",
      "x": 81.97,
      "y": 11.38
    },
    {
      "name": "小油坑",
      "x": 35.9,
      "y": 55.49
    },
    {
      "name": "磺嘴山",
      "x": 33.41,
      "y": 27.72
    }
  ],
  "yama/datunshan-2025/KCS01420.jpg": [
    {
      "name": "小油坑",
      "x": 23.88,
      "y": 62.4
    },
    {
      "name": "七星山",
      "x": 52.48,
      "y": 37.28
    },
    {
      "name": "七星山南峰",
      "x": 68.51,
      "y": 39.08
    },
    {
      "name": "七星山東峰",
      "x": 58.65,
      "y": 39.14
    },
    {
      "name": "磺嘴山",
      "x": 21.71,
      "y": 46.35
    }
  ],
  "yama/datunshan-2025/KCS01478.jpg": [
    {
      "name": "竹子山",
      "x": 60.82,
      "y": 32.29
    }
  ],
  "yama/datunshan-2025/KCS01494.jpg": [
    {
      "name": "大屯山",
      "x": 60.82,
      "y": 21.84
    }
  ],
  "yama/datunshan-2025/KCS01515.jpg": [
    {
      "name": "竹子山",
      "x": 48.08,
      "y": 32.59
    }
  ],
  "yama/datunshan-2025/KCS01534.jpg": [
    {
      "name": "觀音山",
      "x": 61.06,
      "y": 31.21
    }
  ],
  "yama/datunshan-2025/KCS02344.jpg": [
    {
      "name": "竹子山",
      "x": 58.17,
      "y": 25.61
    }
  ],
  "yama/datunshan-2025/KCS02357.jpg": [
    {
      "name": "七星山",
      "x": 47.28,
      "y": 12.81
    },
    {
      "name": "小油坑",
      "x": 42.39,
      "y": 38.41
    }
  ],
  "yama/datunshan-2025/KCS02374.jpg": [
    {
      "name": "觀音山",
      "x": 65.22,
      "y": 32.46
    }
  ],
  "yama/datunshan-2025/KCS02378.jpg": [
    {
      "name": "七星山",
      "x": 49.6,
      "y": 33.66
    },
    {
      "name": "小油坑",
      "x": 21.96,
      "y": 58.78
    },
    {
      "name": "磺嘴山",
      "x": 20.03,
      "y": 41.83
    }
  ]
}